Workbook

Sheet Cover
B2: NIKE'S NEXT RUN
B3: Integrated Three-Statement, Scenario & Valuation Model | Prepared by Daniel Sibanda
B5: Board-level analysis of Nike's operating recovery, capital allocation and shareholder value creation.
B7: MODEL OVERVIEW
C9: Company | D9: NIKE, Inc. (NYSE: NKE)
C10: Fiscal year end | D10: May 31
C11: Model periods | D11: FY2022A–FY2031F
C12: Currency / units | D12: USD millions, except per-share data
C13: Valuation date | D13: 2026-08-21
C14: Prepared by | D14: Daniel Sibanda
B16: TABLE OF CONTENTS
C18: Worksheet | D18: Purpose | E18: Model Area | F18: Navigation
C19: Cover | D19: Instructions, checks, sources and disclaimer | E19: Control | F19: =HYPERLINK("#'Cover'!B2","Go to Cover") -> Go to Cover
C20: Dashboard | D20: Executive outputs, KPIs, charts and recommendation | E20: Output | F20: =HYPERLINK("#'Dashboard'!B2","Go to Dashboard") -> Go to Dashboard
C21: Inputs | D21: Scenario drivers, historical data and source links | E21: Input | F21: =HYPERLINK("#'Inputs'!B2","Go to Inputs") -> Go to Inputs
C22: Model | D22: Integrated statements, DCF and investment appraisal | E22: Calculation | F22: =HYPERLINK("#'Model'!B2","Go to Model") -> Go to Model
B24: MODELING CONVENTIONS & INSTRUCTIONS
C26: 1 | D26: Blue font | E26: Hardcoded filing data and analyst assumptions. Status and source fields identify what is reported, derived or combined.
C27: 2 | D27: Black font | E27: All formulas and calculations are black, including formulas linked to another worksheet.
C28: 3 | D28: Actual / Forecast | E28: Gray columns are actuals; light-blue columns are forecasts.
C29: 4 | D29: Sign convention | E29: Negative figures display in brackets; zeros display as a dash.
C30: 5 | D30: Scenario controls | E30: Use the Dashboard master scenario plus the four independent driver switches for revenue, pricing / margin, capex and working capital.
C31: 6 | D31: Circularity switch | E31: Default is OFF. ON uses average debt and short-term-investment balances for interest; opening cash is retained to keep the workbook stable and non-iterative.
C32: 7 | D32: NPV / XIRR | E32: Project appraisal uses Excel NPV and date-specific XIRR formulas.
C33: 8 | D33: Navigation | E33: Column A is intentionally blank; use the header and table-of-contents links.
B35: MODEL CHECKS
C37: Check | D37: Result | E37: Tolerance | F37: Status
C38: Balance sheet | D38: =Model!N104 -> 0 | E38: 0.1 | F38: =IF(ABS(D38)<=E38,"OK","CHECK") -> OK
C39: Cash flow reconciliation | D39: =Model!N136 -> 0 | E39: 0.1 | F39: =IF(ABS(D39)<=E39,"OK","CHECK") -> OK
C40: Debt roll-forward | D40: =Model!N168 -> 0 | E40: 0.1 | F40: =IF(ABS(D40)<=E40,"OK","CHECK") -> OK
C41: PP&E roll-forward | D41: =Model!N169 -> 0 | E41: 0.1 | F41: =IF(ABS(D41)<=E41,"OK","CHECK") -> OK
C42: Scenario selection | D42: =Model!N170 -> 0 | E42: 0.1 | F42: =IF(ABS(D42)<=E42,"OK","CHECK") -> OK
C43: DCF bridge | D43: =Model!N171 -> 0 | E43: 0.1 | F43: =IF(ABS(D43)<=E43,"OK","CHECK") -> OK
C44: Circularity control | D44: =Inputs!D10 -> 0 | E44: 0 or 1 | F44: =IF(OR(D44=0,D44=1),"OK","CHECK") -> OK
C45: Historical filing reconciliation | D45: =COUNTIF(Inputs!H262:H301,"CHECK") -> 0 | E45: 0 | F45: =IF(D45=0,"OK","CHECK") -> OK
C46: OVERALL MODEL STATUS | E46: =IF(COUNTIF(F38:F45,"CHECK")=0,"MODEL OK","REVIEW CHECKS") -> MODEL OK
B49: DISCLAIMER
C51: This workbook is an independent educational and portfolio analysis prepared by Daniel Sibanda. Historical information is drawn from publicly available NIKE, Inc. SEC filings and investor materials. Forecasts, scenarios, valuation assumptions and Project Next Run economics are analyst assumptions and do not represent company guidance. This model is not investment advice and should not be relied upon for securities trading or other investment decisions.
B57: VERSION HISTORY
C59: Version | D59: Date | E59: Prepared by | F59: Change summary
C60: 1.0 | D60: 2026-08-21 | E60: Daniel Sibanda | F60: Initial integrated three-statement, DCF, project NPV/XIRR and trading comps model
C61: 1.1 | D61: 2026-08-22 | E61: Daniel Sibanda | F61: Filing audit, full historical cash-flow detail, assumption register, Dashboard dropdown and precedent transactions
C62: 1.2 | D62: 2026-08-22 | E62: Daniel Sibanda | F62: Institutional valuation set, driver switches, tax/share schedules, sensitivity grid and football-field analysis
C63: 1.3 | D63: 2026-08-22 | E63: Daniel Sibanda | F63: Rebuilt controls and dashboard; populated historical drivers; made Adidas and Puma visible; added a native floating football-field chart

Sheet Dashboard
B2: NIKE'S NEXT RUN — EXECUTIVE DASHBOARD
B3: Operating Recovery, Scenario Performance & Valuation | Prepared by Daniel Sibanda
O5: Cover | P5: Dashboard | Q5: Inputs | R5: Model
B7: EXECUTIVE DECISION SUMMARY
C9: SCENARIO ▼ | G9: CIRCULARITY SWITCH ▼ | K9: MODEL STATUS | O9: DCF VALUE / SHARE | S9: CURRENT PRICE
C10: Next Run | G10: OFF | K10: =IF(AND(Model!N172="OK",COUNTIF(Inputs!H262:H301,"CHECK")=0),"OK","CHECK") -> OK | O10: =Model!N160 -> 57.200882 | S10: =Inputs!D152 -> 40.76
C14: =IF(Model!N162>Inputs!$M$150,"RECOMMENDATION: APPROVE PROJECT NEXT RUN WITH MILESTONE-BASED FUNDING",IF(Model!N162>0%,"RECOMMENDATION: APPROVE SELECTIVELY — PROTECT MARGINS AND CASH","RECOMMENDATION: DEFER AND REASSESS CAPITAL ALLOCATION")) -> RECOMMENDATION: APPROVE PROJECT NEXT RUN WITH MILESTONE-BASED FUNDING
B16: FINANCIAL OUTLOOK — SAME-YEAR COLUMN ALIGNMENT
C18: Metric | D18: 2026A | E18: 2027F | F18: 2028F | G18: 2029F | H18: 2030F | I18: 2031F | K18: Valuation method | O18: Value / share
C19: Revenue | D19: =Model!I16 -> 46398 | E19: =Model!J16 -> 48253.92 | F19: =Model!K16 -> 50666.616 | G19: =Model!L16 -> 53453.28 | H19: =Model!M16 -> 56393.21 | I19: =Model!N16 -> 59494.837 | K19: DCF | O19: =Model!N160 -> 57.200882
C20: EBIT | D20: =Model!I21 -> 3797 | E20: =Model!J21 -> 3956.8214 | F20: =Model!K21 -> 4762.6619 | G20: =Model!L21 -> 5719.5009 | H20: =Model!M21 -> 6654.3988 | I20: =Model!N21 -> 7555.8443 | K20: P/E comparables | O20: =Model!L199 -> 23.03259
C21: Net income | D21: =Model!I28 -> 3108 | E21: =Model!J28 -> 2995.4395 | F21: =Model!K28 -> 3673.1321 | G21: =Model!L28 -> 4479.5618 | H21: =Model!M28 -> 5276.1862 | I21: =Model!N28 -> 6056.3911 | K21: Precedent transactions | O21: =Model!N214 -> 48.245831
C22: Cash from operations | D22: =Model!I122 -> 2868 | E22: =Model!J122 -> 4569.1813 | F22: =Model!K122 -> 5323.0464 | G22: =Model!L122 -> 6124.0375 | H22: =Model!M122 -> 7012.9295 | I22: =Model!N122 -> 7890.5743 | K22: Blended | O22: =Model!L201 -> 46.950394
C23: Unlevered FCF | D23: =Model!I148 -> 1728.9169 | E23: =Model!J148 -> 3228.9865 | F23: =Model!K148 -> 3718.1301 | G23: =Model!L148 -> 4447.3456 | H23: =Model!M148 -> 5241.6236 | I23: =Model!N148 -> 6014.9816 | K23: Project NPV ($mm) | O23: =Model!N188 -> 1228.6829
C24: Diluted EPS | D24: =Model!I30 -> 2.1 | E24: =Model!J30 -> 1.9795952 | F24: =Model!K30 -> 2.44102 | G24: =Model!L30 -> 2.9925763 | H24: =Model!M30 -> 3.5421412 | I24: =Model!N30 -> 4.0847171 | K24: Project XIRR | O24: =Model!N189 -> 0.34866524
B27: INDEPENDENT DRIVER SWITCHES — SELECT BLUE CELLS ▼
C29: Driver | D29: Switch | E29: Applied adjustment | F29: Model impact
C30: Revenue growth | D30: Base | E30: =Inputs!$G$10 -> 0 | F30: Forecast revenue growth
C31: Pricing / gross margin | D31: Base | E31: =Inputs!$G$11 -> 0 | F31: Gross margin
C32: Capex intensity | D32: Base | E32: =Inputs!$G$12 -> 0 | F32: Capex / revenue
C33: Working-capital efficiency | D33: Base | E33: =Inputs!$G$13 -> 0 | F33: DSO and inventory days; DPO moves inversely
B36: INCOME STATEMENT & CASH FLOW VISUALS
B58: FLOATING FOOTBALL FIELD — IMPLIED VALUE / SHARE
C60: Method | D60: Low | E60: High | X60: Method | Y60: Base | Z60: DCF | AA60: Trading comps | AB60: Precedents | AC60: 52-week range
C61: =Model!C262 -> DCF sensitivity | D61: =Model!D262 -> 47.179598 | E61: =Model!E262 -> 77.494247 | X61: =Model!C262 -> DCF sensitivity | Y61: =Model!D262 -> 47.179598 | Z61: =Model!E262-Model!D262 -> 30.314649 | AA61: =0 -> 0 | AB61: =0 -> 0 | AC61: =0 -> 0
C62: =Model!C263 -> Trading comparables P/E | D62: =Model!D263 -> 19.400033 | E62: =Model!E263 -> 38.602106 | X62: =Model!C263 -> Trading comparables P/E | Y62: =Model!D263 -> 19.400033 | Z62: =0 -> 0 | AA62: =Model!E263-Model!D263 -> 19.202073 | AB62: =0 -> 0 | AC62: =0 -> 0
C63: =Model!C264 -> Precedent transactions | D63: =Model!D264 -> 40.578985 | E63: =Model!E264 -> 134.65317 | X63: =Model!C264 -> Precedent transactions | Y63: =Model!D264 -> 40.578985 | Z63: =0 -> 0 | AA63: =0 -> 0 | AB63: =Model!E264-Model!D264 -> 94.074182 | AC63: =0 -> 0
C64: =Model!C265 -> 52-week trading range | D64: =Model!D265 -> 38.86 | E64: =Model!E265 -> 80.17 | X64: =Model!C265 -> 52-week trading range | Y64: =Model!D265 -> 38.86 | Z64: =0 -> 0 | AA64: =0 -> 0 | AB64: =0 -> 0 | AC64: =Model!E265-Model!D265 -> 41.31
C66: Current price | D66: =Inputs!D152 -> 40.76
C68: Precedent ranges include transaction control premiums; no separate premium is added.
B70: DCF SENSITIVITY — TERMINAL GROWTH VS WACC
C72: Terminal growth / WACC | H72: =Model!E251 -> 0.075 | I72: =Model!F251 -> 0.08 | J72: =Model!G251 -> 0.085 | K72: =Model!H251 -> 0.09 | L72: =Model!I251 -> 0.095 | N72: AUDIT NOTE The sensitivity table fully recalculates explicit forecast cash flows, terminal value, the net-debt bridge and forecast diluted shares for every WACC / terminal-growth pair. It is not a percentage applied to the final answer.
C73: =Model!D252 -> 0.02 | H73: =Model!E252 -> 65.220609 | I73: =Model!F252 -> 59.57543 | J73: =Model!G252 -> 54.803344 | K73: =Model!H252 -> 50.717157 | L73: =Model!I252 -> 47.179598
C74: =Model!D253 -> 0.0225 | H74: =Model!E253 -> 67.850674 | I74: =Model!F253 -> 61.736198 | J74: =Model!G253 -> 56.604743 | K74: =Model!H253 -> 52.237756 | L74: =Model!I253 -> 48.476977
C75: =Model!D254 -> 0.025 | H75: =Model!E254 -> 70.743746 | I75: =Model!F254 -> 64.0934 | J75: =Model!G254 -> 58.556259 | K75: =Model!H254 -> 53.875324 | L75: =Model!I254 -> 49.867025
C76: =Model!D255 -> 0.0275 | H76: =Model!E255 -> 73.941352 | I76: =Model!F255 -> 66.675098 | J76: =Model!G255 -> 60.677473 | K76: =Model!H255 -> 55.643897 | L76: =Model!I255 -> 51.36004
C77: =Model!D256 -> 0.03 | H77: =Model!E256 -> 77.494247 | I77: =Model!F256 -> 69.514965 | J77: =Model!G256 -> 62.991524 | K77: =Model!H256 -> 57.559851 | L77: =Model!I256 -> 52.967902
B80: KEY RISKS & MANAGEMENT TRIGGERS
C82: Risk | D82: Metric | E82: Trigger | F82: Management response
C83: Revenue recovery | D83: Revenue growth | E83: < 2% for two periods | F83: Reset inventory buys and demand allocation
C84: Margin quality | D84: Gross margin | E84: < 43% by FY2028F | F84: Accelerate full-price mix and sourcing savings
C85: Capital efficiency | D85: Project XIRR | E85: Below hurdle rate | F85: Pause later investment tranches
C86: Tax timing | D86: Cash tax / book tax | E86: Deferred tax build exceeds plan | F86: Refresh tax-depreciation proxy with tax team
C96: Year | D96: Revenue | E96: Gross profit | F96: EBIT | G96: Net income | J96: Year | K96: Operating | L96: Investing | M96: Financing | N96: Change in cash
C97: 2026A | D97: =Model!I16 -> 46398 | E97: =Model!I18 -> 19911 | F97: =Model!I21 -> 3797 | G97: =Model!I28 -> 3108 | J97: 2026A | K97: =Model!I122 -> 2868 | L97: =Model!I126 -> -488 | M97: =Model!I132 -> -2292 | N97: =Model!I134 -> 99
C98: 2027F | D98: =Model!J16 -> 48253.92 | E98: =Model!J18 -> 20845.693 | F98: =Model!J21 -> 3956.8214 | G98: =Model!J28 -> 2995.4395 | J98: 2027F | K98: =Model!J122 -> 4569.1813 | L98: =Model!J126 -> -1045.2038 | M98: =Model!J132 -> -2797.0357 | N98: =Model!J134 -> 726.94183
C99: 2028F | D99: =Model!K16 -> 50666.616 | E99: =Model!K18 -> 22191.978 | F99: =Model!K21 -> 4762.6619 | G99: =Model!K28 -> 3673.1321 | J99: 2028F | K99: =Model!K122 -> 5323.0464 | L99: =Model!K126 -> -1085.7132 | M99: =Model!K132 -> -3127.3419 | N99: =Model!K134 -> 1109.9913
C100: 2029F | D100: =Model!L16 -> 53453.28 | E100: =Model!L18 -> 23733.256 | F100: =Model!L21 -> 5719.5009 | G100: =Model!L28 -> 4479.5618 | J100: 2029F | K100: =Model!L122 -> 6124.0375 | L100: =Model!L126 -> -1096.4256 | M100: =Model!L132 -> -3537.7371 | N100: =Model!L134 -> 1489.8749
C101: 2030F | D101: =Model!M16 -> 56393.21 | E101: =Model!M18 -> 25320.551 | F101: =Model!M21 -> 6654.3988 | G101: =Model!M28 -> 5276.1862 | J101: 2030F | K101: =Model!M122 -> 7012.9295 | L101: =Model!M126 -> -1097.3958 | M101: =Model!M132 -> -3910.188 | N101: =Model!M134 -> 2005.3457
C102: 2031F | D102: =Model!N16 -> 59494.837 | E102: =Model!N18 -> 26951.161 | F102: =Model!N21 -> 7555.8443 | G102: =Model!N28 -> 6056.3911 | J102: 2031F | K102: =Model!N122 -> 7890.5743 | L102: =Model!N126 -> -1095.1561 | M102: =Model!N132 -> -4181.0151 | N102: =Model!N134 -> 2614.403

Sheet Inputs
B2: NIKE'S NEXT RUN — INPUTS
B3: Historical Data, Scenario Drivers, Evidence Register & Valuation Assumptions | Prepared by Daniel Sibanda
N5: Cover | O5: Dashboard | P5: Inputs | Q5: Model
B7: MODEL CONTROLS
C9: Selected scenario | D9: =Dashboard!C10 -> Next Run | F9: Driver overlay | G9: Selected adjustment
C10: Circularity / interest convention | D10: =IF(Dashboard!G10="ON",1,0) -> 0 | F10: Revenue growth | G10: =IF(Dashboard!$D$30="Down",-2%,IF(Dashboard!$D$30="Up",2%,0%)) -> 0
C11: Valuation date | D11: 46255 | F11: Gross margin / pricing | G11: =IF(Dashboard!$D$31="Down",-1%,IF(Dashboard!$D$31="Up",1%,0%)) -> 0
C12: Currency / units | D12: USD millions | F12: Capex / revenue | G12: =IF(Dashboard!$D$32="Down",-0.5%,IF(Dashboard!$D$32="Up",0.5%,0%)) -> 0
C13: Forecast start | D13: FY2027F | F13: DSO / inventory days | G13: =IF(Dashboard!$D$33="Down",3,IF(Dashboard!$D$33="Up",-3,0)) -> 0
C14: Forecast end | D14: FY2031F | F14: DPO days | G14: =IF(Dashboard!$D$33="Down",-2,IF(Dashboard!$D$33="Up",2,0)) -> 0
C15: Historical drivers (FY2022A–FY2026A) are formula-derived from audited actuals below. Forecast drivers (FY2027F–FY2031F) are selected by the Dashboard scenario and driver dropdowns.
B16: SELECTED SCENARIO DRIVERS
C17: Driver | D17: Units | E17: 2022A | F17: 2023A | G17: 2024A | H17: 2025A | I17: 2026A | J17: 2027F | K17: 2028F | L17: 2029F | M17: 2030F | N17: 2031F
C18: Revenue growth | D18: % | E18: 0.048767345 | F18: =F158/E158-1 -> 0.096488975 | G18: =G158/F158-1 -> 0.0028310912 | H18: =H158/G158-1 -> -0.098380125 | I18: =I158/H158-1 -> 0.0019218726 | J18: =IF($D$9="Downside",J47,IF($D$9="Stabilization",J70,IF($D$9="Next Run",J93,J116))) -> 0.04 | K18: =IF($D$9="Downside",K47,IF($D$9="Stabilization",K70,IF($D$9="Next Run",K93,K116))) -> 0.05 | L18: =IF($D$9="Downside",L47,IF($D$9="Stabilization",L70,IF($D$9="Next Run",L93,L116))) -> 0.055 | M18: =IF($D$9="Downside",M47,IF($D$9="Stabilization",M70,IF($D$9="Next Run",M93,M116))) -> 0.055 | N18: =IF($D$9="Downside",N47,IF($D$9="Stabilization",N70,IF($D$9="Next Run",N93,N116))) -> 0.055
C19: Gross margin | D19: % | E19: =E160/E158 -> 0.45983729 | F19: =F160/F158 -> 0.43524611 | G19: =G160/G158 -> 0.44560181 | H19: =H160/H158 -> 0.42734674 | I19: =I160/I158 -> 0.42913488 | J19: =IF($D$9="Downside",J48,IF($D$9="Stabilization",J71,IF($D$9="Next Run",J94,J117))) -> 0.432 | K19: =IF($D$9="Downside",K48,IF($D$9="Stabilization",K71,IF($D$9="Next Run",K94,K117))) -> 0.438 | L19: =IF($D$9="Downside",L48,IF($D$9="Stabilization",L71,IF($D$9="Next Run",L94,L117))) -> 0.444 | M19: =IF($D$9="Downside",M48,IF($D$9="Stabilization",M71,IF($D$9="Next Run",M94,M117))) -> 0.449 | N19: =IF($D$9="Downside",N48,IF($D$9="Stabilization",N71,IF($D$9="Next Run",N94,N117))) -> 0.453
C20: Demand creation / revenue | D20: % | E20: =E161/E158 -> 0.082423464 | F20: =F161/F158 -> 0.079270555 | G20: =G161/G158 -> 0.083427437 | H20: =H161/H158 -> 0.10125462 | I20: =I161/I158 -> 0.10246131 | J20: =IF($D$9="Downside",J49,IF($D$9="Stabilization",J72,IF($D$9="Next Run",J95,J118))) -> 0.105 | K20: =IF($D$9="Downside",K49,IF($D$9="Stabilization",K72,IF($D$9="Next Run",K95,K118))) -> 0.106 | L20: =IF($D$9="Downside",L49,IF($D$9="Stabilization",L72,IF($D$9="Next Run",L95,L118))) -> 0.105 | M20: =IF($D$9="Downside",M49,IF($D$9="Stabilization",M72,IF($D$9="Next Run",M95,M118))) -> 0.104 | N20: =IF($D$9="Downside",N49,IF($D$9="Stabilization",N72,IF($D$9="Next Run",N95,N118))) -> 0.103
C21: Operating overhead / revenue | D21: % | E21: =E162/E158 -> 0.23451081 | F21: =F162/F158 -> 0.24048656 | G21: =G162/G158 -> 0.23930143 | H21: =H162/H158 -> 0.24615086 | I21: =I162/I158 -> 0.24483814 | J21: =IF($D$9="Downside",J50,IF($D$9="Stabilization",J73,IF($D$9="Next Run",J96,J119))) -> 0.245 | K21: =IF($D$9="Downside",K50,IF($D$9="Stabilization",K73,IF($D$9="Next Run",K96,K119))) -> 0.238 | L21: =IF($D$9="Downside",L50,IF($D$9="Stabilization",L73,IF($D$9="Next Run",L96,L119))) -> 0.232 | M21: =IF($D$9="Downside",M50,IF($D$9="Stabilization",M73,IF($D$9="Next Run",M96,M119))) -> 0.227 | N21: =IF($D$9="Downside",N50,IF($D$9="Stabilization",N73,IF($D$9="Next Run",N96,N119))) -> 0.223
C22: DSO | D22: Days | E22: =E193/E158*365 -> 36.468743 | F22: =F193/F158*365 -> 29.439737 | G22: =G193/G158*365 -> 31.460126 | H22: =H193/H158*365 -> 37.178626 | I22: =I193/I158*365 -> 46.657507 | J22: =IF($D$9="Downside",J51,IF($D$9="Stabilization",J74,IF($D$9="Next Run",J97,J120))) -> 44 | K22: =IF($D$9="Downside",K51,IF($D$9="Stabilization",K74,IF($D$9="Next Run",K97,K120))) -> 43 | L22: =IF($D$9="Downside",L51,IF($D$9="Stabilization",L74,IF($D$9="Next Run",L97,L120))) -> 42 | M22: =IF($D$9="Downside",M51,IF($D$9="Stabilization",M74,IF($D$9="Next Run",M97,M120))) -> 41 | N22: =IF($D$9="Downside",N51,IF($D$9="Stabilization",N74,IF($D$9="Next Run",N97,N120))) -> 40
C23: Inventory days | D23: Days | E23: =E194/E159*365 -> 121.80651 | F23: =F194/F159*365 -> 106.67969 | G23: =G194/G159*365 -> 96.380509 | H23: =H194/H159*365 -> 103.07647 | I23: =I194/I159*365 -> 103.36637 | J23: =IF($D$9="Downside",J52,IF($D$9="Stabilization",J75,IF($D$9="Next Run",J98,J121))) -> 101 | K23: =IF($D$9="Downside",K52,IF($D$9="Stabilization",K75,IF($D$9="Next Run",K98,K121))) -> 99 | L23: =IF($D$9="Downside",L52,IF($D$9="Stabilization",L75,IF($D$9="Next Run",L98,L121))) -> 97 | M23: =IF($D$9="Downside",M52,IF($D$9="Stabilization",M75,IF($D$9="Next Run",M98,M121))) -> 96 | N23: =IF($D$9="Downside",N52,IF($D$9="Stabilization",N75,IF($D$9="Next Run",N98,N121))) -> 95
C24: DPO | D24: Days | E24: =E203/E159*365 -> 48.57794 | F24: =F203/F159*365 -> 36.115125 | G24: =G203/G159*365 -> 36.544864 | H24: =H203/H159*365 -> 47.88397 | I24: =I203/I159*365 -> 49.609242 | J24: =IF($D$9="Downside",J53,IF($D$9="Stabilization",J76,IF($D$9="Next Run",J99,J122))) -> 49 | K24: =IF($D$9="Downside",K53,IF($D$9="Stabilization",K76,IF($D$9="Next Run",K99,K122))) -> 50 | L24: =IF($D$9="Downside",L53,IF($D$9="Stabilization",L76,IF($D$9="Next Run",L99,L122))) -> 50 | M24: =IF($D$9="Downside",M53,IF($D$9="Stabilization",M76,IF($D$9="Next Run",M99,M122))) -> 51 | N24: =IF($D$9="Downside",N53,IF($D$9="Stabilization",N76,IF($D$9="Next Run",N99,N122))) -> 52
C25: Prepaids / revenue | D25: % | E25: =E195/E158 -> 0.045579105 | F25: =F195/F158 -> 0.037917098 | G25: =G195/G158 -> 0.036096725 | H25: =H195/H158 -> 0.04329612 | I25: =I195/I158 -> 0.046208888 | J25: =IF($D$9="Downside",J54,IF($D$9="Stabilization",J77,IF($D$9="Next Run",J100,J123))) -> 0.045 | K25: =IF($D$9="Downside",K54,IF($D$9="Stabilization",K77,IF($D$9="Next Run",K100,K123))) -> 0.044 | L25: =IF($D$9="Downside",L54,IF($D$9="Stabilization",L77,IF($D$9="Next Run",L100,L123))) -> 0.043 | M25: =IF($D$9="Downside",M54,IF($D$9="Stabilization",M77,IF($D$9="Next Run",M100,M123))) -> 0.042 | N25: =IF($D$9="Downside",N54,IF($D$9="Stabilization",N77,IF($D$9="Next Run",N100,N123))) -> 0.041
C26: Other assets / revenue | D26: % | E26: =E200/E158 -> 0.081802612 | F26: =F200/F158 -> 0.073608372 | G26: =G200/G158 -> 0.087827577 | H26: =H200/H158 -> 0.11181412 | I26: =I200/I158 -> 0.12228975 | J26: =IF($D$9="Downside",J55,IF($D$9="Stabilization",J78,IF($D$9="Next Run",J101,J124))) -> 0.121 | K26: =IF($D$9="Downside",K55,IF($D$9="Stabilization",K78,IF($D$9="Next Run",K101,K124))) -> 0.119 | L26: =IF($D$9="Downside",L55,IF($D$9="Stabilization",L78,IF($D$9="Next Run",L101,L124))) -> 0.117 | M26: =IF($D$9="Downside",M55,IF($D$9="Stabilization",M78,IF($D$9="Next Run",M101,M124))) -> 0.115 | N26: =IF($D$9="Downside",N55,IF($D$9="Stabilization",N78,IF($D$9="Next Run",N101,N124))) -> 0.113
C27: Accrued liabilities / revenue | D27: % | E27: =E205/E158 -> 0.13316206 | F27: =F205/F158 -> 0.11174024 | G27: =G205/G158 -> 0.11146373 | H27: =H205/H158 -> 0.12775055 | I27: =I205/I158 -> 0.13129876 | J27: =IF($D$9="Downside",J56,IF($D$9="Stabilization",J79,IF($D$9="Next Run",J102,J125))) -> 0.132 | K27: =IF($D$9="Downside",K56,IF($D$9="Stabilization",K79,IF($D$9="Next Run",K102,K125))) -> 0.13 | L27: =IF($D$9="Downside",L56,IF($D$9="Stabilization",L79,IF($D$9="Next Run",L102,L125))) -> 0.128 | M27: =IF($D$9="Downside",M56,IF($D$9="Stabilization",M79,IF($D$9="Next Run",M102,M125))) -> 0.126 | N27: =IF($D$9="Downside",N56,IF($D$9="Stabilization",N79,IF($D$9="Next Run",N102,N125))) -> 0.124
C28: Other liabilities / revenue | D28: % | E28: =E209/E158 -> 0.055940912 | F28: =F209/F158 -> 0.049944354 | G28: =G209/G158 -> 0.050971535 | H28: =H209/H158 -> 0.049428837 | I28: =I209/I158 -> 0.052653132 | J28: =IF($D$9="Downside",J57,IF($D$9="Stabilization",J80,IF($D$9="Next Run",J103,J126))) -> 0.053 | K28: =IF($D$9="Downside",K57,IF($D$9="Stabilization",K80,IF($D$9="Next Run",K103,K126))) -> 0.052 | L28: =IF($D$9="Downside",L57,IF($D$9="Stabilization",L80,IF($D$9="Next Run",L103,L126))) -> 0.051 | M28: =IF($D$9="Downside",M57,IF($D$9="Stabilization",M80,IF($D$9="Next Run",M103,M126))) -> 0.05 | N28: =IF($D$9="Downside",N57,IF($D$9="Stabilization",N80,IF($D$9="Next Run",N103,N126))) -> 0.049
C29: Capex / revenue | D29: % | E29: =E180/E158 -> 0.016227788 | F29: =F180/F158 -> 0.018919499 | G29: =G180/G158 -> 0.015809353 | H29: =H180/H158 -> 0.0092854521 | I29: =I180/I158 -> 0.014742015 | J29: =IF($D$9="Downside",J58,IF($D$9="Stabilization",J81,IF($D$9="Next Run",J104,J127))) -> 0.022 | K29: =IF($D$9="Downside",K58,IF($D$9="Stabilization",K81,IF($D$9="Next Run",K104,K127))) -> 0.021 | L29: =IF($D$9="Downside",L58,IF($D$9="Stabilization",L81,IF($D$9="Next Run",L104,L127))) -> 0.02 | M29: =IF($D$9="Downside",M58,IF($D$9="Stabilization",M81,IF($D$9="Next Run",M104,M127))) -> 0.019 | N29: =IF($D$9="Downside",N58,IF($D$9="Stabilization",N81,IF($D$9="Next Run",N104,N127))) -> 0.018
C30: D&A / revenue | D30: % | E30: =E170/E158 -> 0.015350032 | F30: =F170/F158 -> 0.013725911 | G30: =G170/G158 -> 0.015497839 | H30: =H170/H158 -> 0.016735408 | I30: =I170/I158 -> 0.016099832 | J30: =IF($D$9="Downside",J59,IF($D$9="Stabilization",J82,IF($D$9="Next Run",J105,J128))) -> 0.016 | K30: =IF($D$9="Downside",K59,IF($D$9="Stabilization",K82,IF($D$9="Next Run",K105,K128))) -> 0.016 | L30: =IF($D$9="Downside",L59,IF($D$9="Stabilization",L82,IF($D$9="Next Run",L105,L128))) -> 0.016 | M30: =IF($D$9="Downside",M59,IF($D$9="Stabilization",M82,IF($D$9="Next Run",M105,M128))) -> 0.016 | N30: =IF($D$9="Downside",N59,IF($D$9="Stabilization",N82,IF($D$9="Next Run",N105,N128))) -> 0.016
C31: Stock compensation / revenue | D31: % | E31: =E171/E158 -> 0.013658745 | F31: =F171/F158 -> 0.014741199 | G31: =G171/G158 -> 0.015653596 | H31: =H171/H158 -> 0.015310199 | I31: =I171/I158 -> 0.015410147 | J31: =IF($D$9="Downside",J60,IF($D$9="Stabilization",J83,IF($D$9="Next Run",J106,J129))) -> 0.015 | K31: =IF($D$9="Downside",K60,IF($D$9="Stabilization",K83,IF($D$9="Next Run",K106,K129))) -> 0.015 | L31: =IF($D$9="Downside",L60,IF($D$9="Stabilization",L83,IF($D$9="Next Run",L106,L129))) -> 0.015 | M31: =IF($D$9="Downside",M60,IF($D$9="Stabilization",M83,IF($D$9="Next Run",M106,M129))) -> 0.015 | N31: =IF($D$9="Downside",N60,IF($D$9="Stabilization",N83,IF($D$9="Next Run",N106,N129))) -> 0.015
C32: Dividend payout | D32: % | E32: =E184/E167 -> 0.30383725 | F32: =F184/F167 -> 0.39684418 | G32: =G184/G167 -> 0.38052632 | H32: =H184/H167 -> 0.71450761 | I32: =I184/I167 -> 0.77445302 | J32: =IF($D$9="Downside",J61,IF($D$9="Stabilization",J84,IF($D$9="Next Run",J107,J130))) -> 0.65 | K32: =IF($D$9="Downside",K61,IF($D$9="Stabilization",K84,IF($D$9="Next Run",K107,K130))) -> 0.62 | L32: =IF($D$9="Downside",L61,IF($D$9="Stabilization",L84,IF($D$9="Next Run",L107,L130))) -> 0.6 | M32: =IF($D$9="Downside",M61,IF($D$9="Stabilization",M84,IF($D$9="Next Run",M107,M130))) -> 0.58 | N32: =IF($D$9="Downside",N61,IF($D$9="Stabilization",N84,IF($D$9="Next Run",N107,N130))) -> 0.55
C33: Share repurchases | D33: $mm | E33: =E185 -> 4014 | F33: =F185 -> 5480 | G33: =G185 -> 4250 | H33: =H185 -> 2985 | I33: =I185 -> 146 | J33: =IF($D$9="Downside",J62,IF($D$9="Stabilization",J85,IF($D$9="Next Run",J108,J131))) -> 500 | K33: =IF($D$9="Downside",K62,IF($D$9="Stabilization",K85,IF($D$9="Next Run",K108,K131))) -> 500 | L33: =IF($D$9="Downside",L62,IF($D$9="Stabilization",L85,IF($D$9="Next Run",L108,L131))) -> 500 | M33: =IF($D$9="Downside",M62,IF($D$9="Stabilization",M85,IF($D$9="Next Run",M108,M131))) -> 500 | N33: =IF($D$9="Downside",N62,IF($D$9="Stabilization",N85,IF($D$9="Next Run",N108,N131))) -> 500
C34: Debt repayment | D34: $mm | E34: =-E182 -> -15 | F34: =-F182 -> 504 | G34: =-G182 -> 0 | H34: =-H182 -> 1000 | I34: =-I182 -> 0 | J34: =IF($D$9="Downside",J63,IF($D$9="Stabilization",J86,IF($D$9="Next Run",J109,J132))) -> 500 | K34: =IF($D$9="Downside",K63,IF($D$9="Stabilization",K86,IF($D$9="Next Run",K109,K132))) -> 500 | L34: =IF($D$9="Downside",L63,IF($D$9="Stabilization",L86,IF($D$9="Next Run",L109,L132))) -> 500 | M34: =IF($D$9="Downside",M63,IF($D$9="Stabilization",M86,IF($D$9="Next Run",M109,M132))) -> 500 | N34: =IF($D$9="Downside",N63,IF($D$9="Stabilization",N86,IF($D$9="Next Run",N109,N132))) -> 500
C35: Stock issuance | D35: $mm | E35: =E183 -> 1000 | F35: =F183 -> 549 | G35: =G183 -> 531 | H35: =H183 -> 465 | I35: =I183 -> 261 | J35: =IF($D$9="Downside",J64,IF($D$9="Stabilization",J87,IF($D$9="Next Run",J110,J133))) -> 150 | K35: =IF($D$9="Downside",K64,IF($D$9="Stabilization",K87,IF($D$9="Next Run",K110,K133))) -> 150 | L35: =IF($D$9="Downside",L64,IF($D$9="Stabilization",L87,IF($D$9="Next Run",L110,L133))) -> 150 | M35: =IF($D$9="Downside",M64,IF($D$9="Stabilization",M87,IF($D$9="Next Run",M110,M133))) -> 150 | N35: =IF($D$9="Downside",N64,IF($D$9="Stabilization",N87,IF($D$9="Next Run",N110,N133))) -> 150
C36: Short-term investments / revenue | D36: % | E36: =E192/E158 -> 0.094690644 | F36: =F192/F158 -> 0.063143097 | G36: =G192/G158 -> 0.033526732 | H36: =H192/H158 -> 0.036429204 | I36: =I192/I158 -> 0.031553084 | J36: =IF($D$9="Downside",J65,IF($D$9="Stabilization",J88,IF($D$9="Next Run",J111,J134))) -> 0.03 | K36: =IF($D$9="Downside",K65,IF($D$9="Stabilization",K88,IF($D$9="Next Run",K111,K134))) -> 0.029 | L36: =IF($D$9="Downside",L65,IF($D$9="Stabilization",L88,IF($D$9="Next Run",L111,L134))) -> 0.028 | M36: =IF($D$9="Downside",M65,IF($D$9="Stabilization",M88,IF($D$9="Next Run",M111,M134))) -> 0.027 | N36: =IF($D$9="Downside",N65,IF($D$9="Stabilization",N88,IF($D$9="Next Run",N111,N134))) -> 0.026
C37: Lease assets / revenue | D37: % | E37: =E197/E158 -> 0.062641833 | F37: =F197/F158 -> 0.057070894 | G37: =G197/G158 -> 0.0529185 | H37: =H197/H158 -> 0.05856313 | I37: =I197/I158 -> 0.06116643 | J37: =IF($D$9="Downside",J66,IF($D$9="Stabilization",J89,IF($D$9="Next Run",J112,J135))) -> 0.06 | K37: =IF($D$9="Downside",K66,IF($D$9="Stabilization",K89,IF($D$9="Next Run",K112,K135))) -> 0.058 | L37: =IF($D$9="Downside",L66,IF($D$9="Stabilization",L89,IF($D$9="Next Run",L112,L135))) -> 0.056 | M37: =IF($D$9="Downside",M66,IF($D$9="Stabilization",M89,IF($D$9="Next Run",M112,M135))) -> 0.054 | N37: =IF($D$9="Downside",N66,IF($D$9="Stabilization",N89,IF($D$9="Next Run",N112,N135))) -> 0.052
B45: DOWNSIDE SCENARIO
J46: 2027F | K46: 2028F | L46: 2029F | M46: 2030F | N46: 2031F
C47: Revenue growth | D47: % | J47: -0.02 | K47: 0 | L47: 0.02 | M47: 0.03 | N47: 0.03
C48: Gross margin | D48: % | J48: 0.42 | K48: 0.422 | L48: 0.425 | M48: 0.428 | N48: 0.43
C49: Demand creation / revenue | D49: % | J49: 0.105 | K49: 0.104 | L49: 0.103 | M49: 0.102 | N49: 0.101
C50: Operating overhead / revenue | D50: % | J50: 0.25 | K50: 0.248 | L50: 0.245 | M50: 0.242 | N50: 0.24
C51: DSO | D51: Days | J51: 47 | K51: 46 | L51: 45 | M51: 44 | N51: 43
C52: Inventory days | D52: Days | J52: 108 | K52: 106 | L52: 104 | M52: 102 | N52: 100
C53: DPO | D53: Days | J53: 47 | K53: 47 | L53: 48 | M53: 48 | N53: 49
C54: Prepaids / revenue | D54: % | J54: 0.047 | K54: 0.046 | L54: 0.045 | M54: 0.044 | N54: 0.043
C55: Other assets / revenue | D55: % | J55: 0.125 | K55: 0.123 | L55: 0.121 | M55: 0.119 | N55: 0.117
C56: Accrued liabilities / revenue | D56: % | J56: 0.135 | K56: 0.134 | L56: 0.133 | M56: 0.132 | N56: 0.131
C57: Other liabilities / revenue | D57: % | J57: 0.055 | K57: 0.054 | L57: 0.053 | M57: 0.052 | N57: 0.051
C58: Capex / revenue | D58: % | J58: 0.016 | K58: 0.016 | L58: 0.016 | M58: 0.016 | N58: 0.016
... C66: Lease assets / revenue | D66: % | J66: 0.061 | K66: 0.061 | L66: 0.061 | M66: 0.061 | N66: 0.061
B68: STABILIZATION SCENARIO
J69: 2027F | K69: 2028F | L69: 2029F | M69: 2030F | N69: 2031F
C70: Revenue growth | D70: % | J70: 0.01 | K70: 0.02 | L70: 0.03 | M70: 0.035 | N70: 0.035
C71: Gross margin | D71: % | J71: 0.426 | K71: 0.428 | L71: 0.43 | M71: 0.432 | N71: 0.434
C72: Demand creation / revenue | D72: % | J72: 0.104 | K72: 0.103 | L72: 0.102 | M72: 0.101 | N72: 0.1
C73: Operating overhead / revenue | D73: % | J73: 0.248 | K73: 0.245 | L73: 0.242 | M73: 0.239 | N73: 0.237
C74: DSO | D74: Days | J74: 45 | K74: 44 | L74: 43 | M74: 42 | N74: 42
C75: Inventory days | D75: Days | J75: 104 | K75: 102 | L75: 100 | M75: 98 | N75: 97
C76: DPO | D76: Days | J76: 48 | K76: 48 | L76: 49 | M76: 49 | N76: 50
C77: Prepaids / revenue | D77: % | J77: 0.046 | K77: 0.045 | L77: 0.044 | M77: 0.043 | N77: 0.042
C78: Other assets / revenue | D78: % | J78: 0.123 | K78: 0.121 | L78: 0.119 | M78: 0.117 | N78: 0.115
C79: Accrued liabilities / revenue | D79: % | J79: 0.133 | K79: 0.132 | L79: 0.131 | M79: 0.13 | N79: 0.129
C80: Other liabilities / revenue | D80: % | J80: 0.054 | K80: 0.053 | L80: 0.052 | M80: 0.051 | N80: 0.05
C81: Capex / revenue | D81: % | J81: 0.017 | K81: 0.017 | L81: 0.017 | M81: 0.017 | N81: 0.017
... C89: Lease assets / revenue | D89: % | J89: 0.06 | K89: 0.059 | L89: 0.058 | M89: 0.057 | N89: 0.056
B91: NEXT RUN SCENARIO
J92: 2027F | K92: 2028F | L92: 2029F | M92: 2030F | N92: 2031F
C93: Revenue growth | D93: % | J93: 0.04 | K93: 0.05 | L93: 0.055 | M93: 0.055 | N93: 0.055
C94: Gross margin | D94: % | J94: 0.432 | K94: 0.438 | L94: 0.444 | M94: 0.449 | N94: 0.453
C95: Demand creation / revenue | D95: % | J95: 0.105 | K95: 0.106 | L95: 0.105 | M95: 0.104 | N95: 0.103
C96: Operating overhead / revenue | D96: % | J96: 0.245 | K96: 0.238 | L96: 0.232 | M96: 0.227 | N96: 0.223
C97: DSO | D97: Days | J97: 44 | K97: 43 | L97: 42 | M97: 41 | N97: 40
C98: Inventory days | D98: Days | J98: 101 | K98: 99 | L98: 97 | M98: 96 | N98: 95
C99: DPO | D99: Days | J99: 49 | K99: 50 | L99: 50 | M99: 51 | N99: 52
C100: Prepaids / revenue | D100: % | J100: 0.045 | K100: 0.044 | L100: 0.043 | M100: 0.042 | N100: 0.041
C101: Other assets / revenue | D101: % | J101: 0.121 | K101: 0.119 | L101: 0.117 | M101: 0.115 | N101: 0.113
C102: Accrued liabilities / revenue | D102: % | J102: 0.132 | K102: 0.13 | L102: 0.128 | M102: 0.126 | N102: 0.124
C103: Other liabilities / revenue | D103: % | J103: 0.053 | K103: 0.052 | L103: 0.051 | M103: 0.05 | N103: 0.049
C104: Capex / revenue | D104: % | J104: 0.022 | K104: 0.021 | L104: 0.02 | M104: 0.019 | N104: 0.018
... C112: Lease assets / revenue | D112: % | J112: 0.06 | K112: 0.058 | L112: 0.056 | M112: 0.054 | N112: 0.052
B114: ACCELERATED SCENARIO
J115: 2027F | K115: 2028F | L115: 2029F | M115: 2030F | N115: 2031F
C116: Revenue growth | D116: % | J116: 0.06 | K116: 0.07 | L116: 0.07 | M116: 0.065 | N116: 0.06
C117: Gross margin | D117: % | J117: 0.428 | K117: 0.435 | L117: 0.445 | M117: 0.452 | N117: 0.458
C118: Demand creation / revenue | D118: % | J118: 0.11 | K118: 0.112 | L118: 0.11 | M118: 0.108 | N118: 0.106
C119: Operating overhead / revenue | D119: % | J119: 0.25 | K119: 0.24 | L119: 0.23 | M119: 0.223 | N119: 0.218
C120: DSO | D120: Days | J120: 44 | K120: 43 | L120: 42 | M120: 41 | N120: 40
C121: Inventory days | D121: Days | J121: 104 | K121: 100 | L121: 96 | M121: 92 | N121: 89
C122: DPO | D122: Days | J122: 48 | K122: 49 | L122: 50 | M122: 51 | N122: 52
C123: Prepaids / revenue | D123: % | J123: 0.047 | K123: 0.046 | L123: 0.044 | M123: 0.042 | N123: 0.04
C124: Other assets / revenue | D124: % | J124: 0.124 | K124: 0.121 | L124: 0.118 | M124: 0.115 | N124: 0.112
C125: Accrued liabilities / revenue | D125: % | J125: 0.135 | K125: 0.132 | L125: 0.129 | M125: 0.126 | N125: 0.123
C126: Other liabilities / revenue | D126: % | J126: 0.055 | K126: 0.053 | L126: 0.051 | M126: 0.049 | N126: 0.047
C127: Capex / revenue | D127: % | J127: 0.028 | K127: 0.026 | L127: 0.024 | M127: 0.022 | N127: 0.02
... C135: Lease assets / revenue | D135: % | J135: 0.062 | K135: 0.06 | L135: 0.058 | M135: 0.056 | N135: 0.054
B138: VALUATION & PROJECT ASSUMPTIONS
C140: Risk-free rate | D140: 0.0474 | F140: Project driver | G140: 2027F | H140: 2028F | I140: 2029F | J140: 2030F | K140: 2031F | L140: Additional model assumption | M140: Value | O140: NKE market range | P140: Value / share
C141: Equity risk premium | D141: 0.0428 | F141: Investment ($mm) | G141: 500 | H141: 450 | I141: 300 | J141: 0 | K141: 0 | L141: Current debt / notes balance | M141: 0 | O141: 52-week low | P141: 38.86
C142: Beta | D142: 1.05 | F142: Incremental revenue uplift | G142: 0 | H142: 0.01 | I142: 0.02 | J142: 0.03 | K142: 0.04 | L142: Current lease liability / lease asset | M142: 0.15 | O142: 52-week high | P142: 80.17
C143: Pre-tax cost of debt | D143: 0.0534 | F143: Project dates | G143: 46538 | H143: 46904 | I143: 47269 | J143: 47634 | K143: 47999 | L143: Taxes payable / tax expense | M143: 0.5
C144: Debt weight | D144: 0.12 | L144: DCF valuation weight | M144: 0.7
C145: Equity weight | D145: 0.88 | L145: Trading comps weight | M145: 0.3
...

Sheet Model
B2: NIKE'S NEXT RUN — INTEGRATED MODEL
B3: Three-Statement Forecast, Investment Appraisal & Valuation | Prepared by Daniel Sibanda
K5: Cover | L5: Dashboard | M5: Inputs | N5: Model
C7: Line item | D7: Units | E7: 2022A | F7: 2023A | G7: 2024A | H7: 2025A | I7: 2026A | J7: 2027F | K7: 2028F | L7: 2029F | M7: 2030F | N7: 2031F
B9: OPERATING MODEL & INCOME STATEMENT
C11: Revenue growth | D11: % | E11: ="" | F11: =F16/E16-1 -> 0.096488975 | G11: =G16/F16-1 -> 0.0028310912 | H11: =H16/G16-1 -> -0.098380125 | I11: =I16/H16-1 -> 0.0019218726 | J11: =Inputs!J18+Inputs!$G$10 -> 0.04 | K11: =Inputs!K18+Inputs!$G$10 -> 0.05 | L11: =Inputs!L18+Inputs!$G$10 -> 0.055 | M11: =Inputs!M18+Inputs!$G$10 -> 0.055 | N11: =Inputs!N18+Inputs!$G$10 -> 0.055
C12: Gross margin | D12: % | E12: =E18/E16 -> 0.45983729 | F12: =F18/F16 -> 0.43524611 | G12: =G18/G16 -> 0.44560181 | H12: =H18/H16 -> 0.42734674 | I12: =I18/I16 -> 0.42913488 | J12: =Inputs!J19+Inputs!$G$11 -> 0.432 | K12: =Inputs!K19+Inputs!$G$11 -> 0.438 | L12: =Inputs!L19+Inputs!$G$11 -> 0.444 | M12: =Inputs!M19+Inputs!$G$11 -> 0.449 | N12: =Inputs!N19+Inputs!$G$11 -> 0.453
C13: Demand creation / revenue | D13: % | E13: =E19/E16 -> 0.082423464 | F13: =F19/F16 -> 0.079270555 | G13: =G19/G16 -> 0.083427437 | H13: =H19/H16 -> 0.10125462 | I13: =I19/I16 -> 0.10246131 | J13: =Inputs!J20 -> 0.105 | K13: =Inputs!K20 -> 0.106 | L13: =Inputs!L20 -> 0.105 | M13: =Inputs!M20 -> 0.104 | N13: =Inputs!N20 -> 0.103
C14: Operating overhead / revenue | D14: % | E14: =E20/E16 -> 0.23451081 | F14: =F20/F16 -> 0.24048656 | G14: =G20/G16 -> 0.23930143 | H14: =H20/H16 -> 0.24615086 | I14: =I20/I16 -> 0.24483814 | J14: =Inputs!J21 -> 0.245 | K14: =Inputs!K21 -> 0.238 | L14: =Inputs!L21 -> 0.232 | M14: =Inputs!M21 -> 0.227 | N14: =Inputs!N21 -> 0.223
C16: Revenue | D16: $mm | E16: =Inputs!E158 -> 46710 | F16: =Inputs!F158 -> 51217 | G16: =Inputs!G158 -> 51362 | H16: =Inputs!H158 -> 46309 | I16: =Inputs!I158 -> 46398 | J16: =I16*(1+J11) -> 48253.92 | K16: =J16*(1+K11) -> 50666.616 | L16: =K16*(1+L11) -> 53453.28 | M16: =L16*(1+M11) -> 56393.21 | N16: =M16*(1+N11) -> 59494.837
C17: Cost of sales | D17: $mm | E17: =Inputs!E159 -> 25231 | F17: =Inputs!F159 -> 28925 | G17: =Inputs!G159 -> 28475 | H17: =Inputs!H159 -> 26519 | I17: =Inputs!I159 -> 26487 | J17: =J16-J18 -> 27408.227 | K17: =K16-K18 -> 28474.638 | L17: =L16-L18 -> 29720.024 | M17: =M16-M18 -> 31072.659 | N17: =N16-N18 -> 32543.676
C18: Gross profit | D18: $mm | E18: =Inputs!E160 -> 21479 | F18: =Inputs!F160 -> 22292 | G18: =Inputs!G160 -> 22887 | H18: =Inputs!H160 -> 19790 | I18: =Inputs!I160 -> 19911 | J18: =J16*J12 -> 20845.693 | K18: =K16*K12 -> 22191.978 | L18: =L16*L12 -> 23733.256 | M18: =M16*M12 -> 25320.551 | N18: =N16*N12 -> 26951.161
C19: Demand creation expense | D19: $mm | E19: =Inputs!E161 -> 3850 | F19: =Inputs!F161 -> 4060 | G19: =Inputs!G161 -> 4285 | H19: =Inputs!H161 -> 4689 | I19: =Inputs!I161 -> 4754 | J19: =J16*J13 -> 5066.6616 | K19: =K16*K13 -> 5370.6613 | L19: =L16*L13 -> 5612.5944 | M19: =M16*M13 -> 5864.8939 | N19: =N16*N13 -> 6127.9682
C20: Operating overhead expense | D20: $mm | E20: =Inputs!E162 -> 10954 | F20: =Inputs!F162 -> 12317 | G20: =Inputs!G162 -> 12291 | H20: =Inputs!H162 -> 11399 | I20: =Inputs!I162 -> 11360 | J20: =J16*J14 -> 11822.21 | K20: =K16*K14 -> 12058.655 | L20: =L16*L14 -> 12401.161 | M20: =M16*M14 -> 12801.259 | N20: =N16*N14 -> 13267.349
C21: EBIT | D21: $mm | E21: =E18-E19-E20 -> 6675 | F21: =F18-F19-F20 -> 5915 | G21: =G18-G19-G20 -> 6311 | H21: =H18-H19-H20 -> 3702 | I21: =I18-I19-I20 -> 3797 | J21: =J18-J19-J20 -> 3956.8214 | K21: =K18-K19-K20 -> 4762.6619 | L21: =L18-L19-L20 -> 5719.5009 | ... N21: =N18-N19-N20 -> 7555.8443
C22: EBIT margin | D22: % | E22: =E21/E16 -> 0.14290302 | F22: =F21/F16 -> 0.115489 | G22: =G21/G16 -> 0.12287294 | H22: =H21/H16 -> 0.079941264 | I22: =I21/I16 -> 0.081835424 | J22: =J21/J16 -> 0.082 | K22: =K21/K16 -> 0.094 | L22: =L21/L16 -> 0.107 | ... N22: =N21/N16 -> 0.127
C23: Interest expense (income), net | D23: $mm | E23: =Inputs!E163 -> 205 | F23: =Inputs!F163 -> -6 | G23: =Inputs!G163 -> -161 | H23: =Inputs!H163 -> -107 | I23: =Inputs!I163 -> -50 | J23: =IF(Inputs!$D$10=0,(I91+I93)*Inputs!$D$143-(I74+I75)*Inputs!$D$155,AVERAGE(I91+I93,J58)*Inputs!$D$143-(I74+AVERAGE(I75,J75))*Inputs!$D$155) -> 198.4278 | K23: =IF(Inputs!$D$10=0,(J91+J93)*Inputs!$D$143-(J74+J75)*Inputs!$D$155,AVERAGE(J91+J93,K58)*Inputs!$D$143-(J74+AVERAGE(J75,K75))*Inputs!$D$155) -> 153.96381 | L23: =IF(Inputs!$D$10=0,(K91+K93)*Inputs!$D$143-(K74+K75)*Inputs!$D$155,AVERAGE(K91+K93,L58)*Inputs!$D$143-(K74+AVERAGE(K75,L75))*Inputs!$D$155) -> 98.971175 | M23: =IF(Inputs!$D$10=0,(L91+L93)*Inputs!$D$143-(L74+L75)*Inputs!$D$155,AVERAGE(L91+L93,M58)*Inputs!$D$143-(L74+AVERAGE(L75,M75))*Inputs!$D$155) -> 34.340304 | N23: =IF(Inputs!$D$10=0,(M91+M93)*Inputs!$D$143-(M74+M75)*Inputs!$D$155,AVERAGE(M91+M93,N58)*Inputs!$D$143-(M74+AVERAGE(M75,N75))*Inputs!$D$155) -> -43.141458
C24: Other (income) expense, net | D24: $mm | E24: =Inputs!E164 -> -181 | F24: =Inputs!F164 -> -280 | G24: =Inputs!G164 -> -228 | H24: =Inputs!H164 -> -76 | I24: =Inputs!I164 -> -53 | J24: =Inputs!$M$149 -> 0 | K24: =Inputs!$M$149 -> 0 | L24: =Inputs!$M$149 -> 0 | M24: =Inputs!$M$149 -> 0 | N24: =Inputs!$M$149 -> 0
C25: Income before taxes | D25: $mm | E25: =Inputs!E165 -> 6651 | F25: =Inputs!F165 -> 6201 | G25: =Inputs!G165 -> 6700 | H25: =Inputs!H165 -> 3885 | I25: =Inputs!I165 -> 3900 | J25: =J21-J23-J24 -> 3758.3936 | K25: =K21-K23-K24 -> 4608.6981 | L25: =L21-L23-L24 -> 5620.5298 | M25: =M21-M23-M24 -> 6620.0585 | N25: =N21-N23-N24 -> 7598.9857
C26: Income tax expense | D26: $mm | E26: =Inputs!E166 -> 605 | F26: =Inputs!F166 -> 1131 | G26: =Inputs!G166 -> 1000 | H26: =Inputs!H166 -> 666 | I26: =Inputs!I166 -> 792 | J26: =J244 -> 762.95417 | K26: =K244 -> 935.56603 | L26: =L244 -> 1140.9679 | M26: =M244 -> 1343.8723 | N26: =N244 -> 1542.5946
C27: Effective tax rate | D27: % | E27: =E26/E25 -> 0.090963765 | F27: =F26/F25 -> 0.18238994 | G27: =G26/G25 -> 0.14925373 | H27: =H26/H25 -> 0.17142857 | I27: =I26/I25 -> 0.20307692 | J27: =IF(J25>0,J26/J25,0%) -> 0.20300007 | K27: =IF(K25>0,K26/K25,0%) -> 0.20300007 | L27: =IF(L25>0,L26/L25,0%) -> 0.20300007 | M27: =IF(M25>0,M26/M25,0%) -> 0.20300007 | N27: =IF(N25>0,N26/N25,0%) -> 0.20300007
C28: Net income | D28: $mm | E28: =Inputs!E167 -> 6046 | F28: =Inputs!F167 -> 5070 | G28: =Inputs!G167 -> 5700 | H28: =Inputs!H167 -> 3219 | I28: =Inputs!I167 -> 3108 | J28: =J25-J26 -> 2995.4395 | K28: =K25-K26 -> 3673.1321 | L28: =L25-L26 -> 4479.5618 | M28: =M25-M26 -> 5276.1862 | N28: =N25-N26 -> 6056.3911
C29: Diluted shares | D29: mm | E29: =Inputs!E169 -> 1610.8 | F29: =Inputs!F169 -> 1569.8 | G29: =Inputs!G169 -> 1529.7 | H29: =Inputs!H169 -> 1487.6 | I29: =Inputs!I169 -> 1481 | J29: =J231 -> 1513.1576 | K29: =K231 -> 1504.753 | L29: =L231 -> 1496.8914 | M29: =M231 -> 1489.5471 | N29: =N231 -> 1482.6953
C30: Diluted EPS | D30: $/share | E30: =Inputs!E168 -> 3.75 | F30: =Inputs!F168 -> 3.23 | G30: =Inputs!G168 -> 3.73 | H30: =Inputs!H168 -> 2.16 | I30: =Inputs!I168 -> 2.1 | J30: =J28/J29 -> 1.9795952 | K30: =K28/K29 -> 2.44102 | L30: =L28/L29 -> 2.9925763 | M30: =M28/M29 -> 3.5421412 | N30: =N28/N29 -> 4.0847171
B33: WORKING CAPITAL & OPERATING BALANCE DRIVERS
C35: DSO | D35: Days | E35: =E39/E16*365 -> 36.468743 | F35: =F39/F16*365 -> 29.439737 | G35: =G39/G16*365 -> 31.460126 | H35: =H39/H16*365 -> 37.178626 | I35: =I39/I16*365 -> 46.657507 | J35: =Inputs!J22+Inputs!$G$13 -> 44 | K35: =Inputs!K22+Inputs!$G$13 -> 43 | L35: =Inputs!L22+Inputs!$G$13 -> 42 | M35: =Inputs!M22+Inputs!$G$13 -> 41 | N35: =Inputs!N22+Inputs!$G$13 -> 40
C36: Inventory days | D36: Days | E36: =E40/E17*365 -> 121.80651 | F36: =F40/F17*365 -> 106.67969 | G36: =G40/G17*365 -> 96.380509 | H36: =H40/H17*365 -> 103.07647 | I36: =I40/I17*365 -> 103.36637 | J36: =Inputs!J23+Inputs!$G$13 -> 101 | K36: =Inputs!K23+Inputs!$G$13 -> 99 | L36: =Inputs!L23+Inputs!$G$13 -> 97 | M36: =Inputs!M23+Inputs!$G$13 -> 96 | N36: =Inputs!N23+Inputs!$G$13 -> 95
C37: DPO | D37: Days | E37: =E42/E17*365 -> 48.57794 | F37: =F42/F17*365 -> 36.115125 | G37: =G42/G17*365 -> 36.544864 | H37: =H42/H17*365 -> 47.88397 | I37: =I42/I17*365 -> 49.609242 | J37: =Inputs!J24+Inputs!$G$14 -> 49 | K37: =Inputs!K24+Inputs!$G$14 -> 50 | L37: =Inputs!L24+Inputs!$G$14 -> 50 | M37: =Inputs!M24+Inputs!$G$14 -> 51 | N37: =Inputs!N24+Inputs!$G$14 -> 52
C39: Accounts receivable | D39: $mm | E39: =Inputs!E193 -> 4667 | F39: =Inputs!F193 -> 4131 | G39: =Inputs!G193 -> 4427 | H39: =Inputs!H193 -> 4717 | I39: =Inputs!I193 -> 5931 | J39: =J16*J35/365 -> 5816.9109 | K39: =K16*K35/365 -> 5968.9438 | L39: =L16*L35/365 -> 6150.7884 | M39: =M16*M35/365 -> 6334.5798 | N39: =N16*N35/365 -> 6519.9821
C40: Inventories | D40: $mm | E40: =Inputs!E194 -> 8420 | F40: =Inputs!F194 -> 8454 | G40: =Inputs!G194 -> 7519 | H40: =Inputs!H194 -> 7489 | I40: =Inputs!I194 -> 7501 | J40: =J17*J36/365 -> 7584.1942 | K40: =K17*K36/365 -> 7723.258 | L40: =L17*L36/365 -> 7898.1981 | M40: =M17*M36/365 -> 8172.5349 | N40: =N17*N36/365 -> 8470.2718
C41: Prepaid & other current assets | D41: $mm | E41: =Inputs!E195 -> 2129 | F41: =Inputs!F195 -> 1942 | G41: =Inputs!G195 -> 1854 | H41: =Inputs!H195 -> 2005 | I41: =Inputs!I195 -> 2144 | J41: =J16*Inputs!J25 -> 2171.4264 | K41: =K16*Inputs!K25 -> 2229.3311 | L41: =L16*Inputs!L25 -> 2298.491 | M41: =M16*Inputs!M25 -> 2368.5148 | N41: =N16*Inputs!N25 -> 2439.2883
C42: Accounts payable | D42: $mm | E42: =Inputs!E203 -> 3358 | F42: =Inputs!F203 -> 2862 | G42: =Inputs!G203 -> 2851 | H42: =Inputs!H203 -> 3479 | I42: =Inputs!I203 -> 3600 | J42: =J17*J37/365 -> 3679.4606 | K42: =K17*K37/365 -> 3900.6354 | L42: =L17*L37/365 -> 4071.2361 | M42: =M17*M37/365 -> 4341.6592 | N42: =N17*N37/365 -> 4636.3593
C43: Accrued liabilities | D43: $mm | E43: =Inputs!E205 -> 6220 | F43: =Inputs!F205 -> 5723 | G43: =Inputs!G205 -> 5725 | H43: =Inputs!H205 -> 5916 | I43: =Inputs!I205 -> 6092 | J43: =J16*Inputs!J27 -> 6369.5174 | K43: =K16*Inputs!K27 -> 6586.6601 | L43: =L16*Inputs!L27 -> 6842.0198 | M43: =M16*Inputs!M27 -> 7105.5445 | N43: =N16*Inputs!N27 -> 7377.3598
C44: Income taxes payable | D44: $mm | E44: =Inputs!E206 -> 222 | F44: =Inputs!F206 -> 240 | G44: =Inputs!G206 -> 534 | H44: =Inputs!H206 -> 669 | I44: =Inputs!I206 -> 377 | J44: =J26*Inputs!$M$143 -> 381.47709 | K44: =K26*Inputs!$M$143 -> 467.78302 | L44: =L26*Inputs!$M$143 -> 570.48397 | M44: =M26*Inputs!$M$143 -> 671.93617 | N44: =N26*Inputs!$M$143 -> 771.29732
C45: Net operating working capital | D45: $mm | E45: =SUM(E39:E41)-SUM(E42:E44) -> 5416 | F45: =SUM(F39:F41)-SUM(F42:F44) -> 5702 | G45: =SUM(G39:G41)-SUM(G42:G44) -> 4690 | H45: =SUM(H39:H41)-SUM(H42:H44) -> 4147 | I45: =SUM(I39:I41)-SUM(I42:I44) -> 5507 | J45: =SUM(J39:J41)-SUM(J42:J44) -> 5142.0764 | K45: =SUM(K39:K41)-SUM(K42:K44) -> 4966.4545 | L45: =SUM(L39:L41)-SUM(L42:L44) -> 4863.7376 | ... N45: =SUM(N39:N41)-SUM(N42:N44) -> 4644.5258
C46: Change in NOWC | D46: $mm | E46: ="" | F46: =F45-E45 -> 286 | G46: =G45-F45 -> -1012 | H46: =H45-G45 -> -543 | I46: =I45-H45 -> 1360 | J46: =J45-I45 -> -364.92357 | K46: =K45-J45 -> -175.62195 | L46: =L45-K45 -> -102.71691 | M46: =M45-L45 -> -107.24786 | N46: =N45-M45 -> -111.96387
B49: PP&E, DEBT & EQUITY SCHEDULES
C51: Beginning PP&E | D51: $mm | E51: ="" | F51: =E54 -> 4791 | G51: =F54 -> 5081 | H51: =G54 -> 5000 | I51: =H54 -> 4828 | J51: =I54 -> 4796 | K51: =J54 -> 5085.5235 | L51: =K54 -> 5338.8566 | M51: =L54 -> 5552.6697 | N51: =M54 -> 5721.8494
C52: Capital expenditures | D52: $mm | E52: =Inputs!E180 -> 758 | F52: =Inputs!F180 -> 969 | G52: =Inputs!G180 -> 812 | H52: =Inputs!H180 -> 430 | I52: =Inputs!I180 -> 684 | J52: =J16*(Inputs!J29+Inputs!$G$12) -> 1061.5862 | K52: =K16*(Inputs!K29+Inputs!$G$12) -> 1063.9989 | L52: =L16*(Inputs!L29+Inputs!$G$12) -> 1069.0656 | M52: =M16*(Inputs!M29+Inputs!$G$12) -> 1071.471 | N52: =N16*(Inputs!N29+Inputs!$G$12) -> 1070.9071
C53: Depreciation & amortization | D53: $mm | E53: =Inputs!E170 -> 717 | F53: =Inputs!F170 -> 703 | G53: =Inputs!G170 -> 796 | H53: =Inputs!H170 -> 775 | I53: =Inputs!I170 -> 747 | J53: =J16*Inputs!J30 -> 772.06272 | K53: =K16*Inputs!K30 -> 810.66586 | L53: =L16*Inputs!L30 -> 855.25248 | M53: =M16*Inputs!M30 -> 902.29136 | N53: =N16*Inputs!N30 -> 951.91739
C54: Ending PP&E | D54: $mm | E54: =Inputs!E196 -> 4791 | F54: =Inputs!F196 -> 5081 | G54: =Inputs!G196 -> 5000 | H54: =Inputs!H196 -> 4828 | I54: =Inputs!I196 -> 4796 | J54: =J51+J52-J53 -> 5085.5235 | K54: =K51+K52-K53 -> 5338.8566 | L54: =L51+L52-L53 -> 5552.6697 | M54: =M51+M52-M53 -> 5721.8494 | N54: =N51+N52-N53 -> 5840.839
C56: Beginning debt | D56: $mm | E56: ="" | F56: =E58 -> 9430 | G56: =F58 -> 8933 | H56: =G58 -> 8909 | I56: =H58 -> 7961 | J56: =I58 -> 7942 | K56: =J58 -> 7442 | L56: =K58 -> 6942 | M56: =L58 -> 6442 | N56: =M58 -> 5942
C57: Debt repayment | D57: $mm | E57: =0 -> 0 | F57: =0 -> 0 | G57: =0 -> 0 | H57: =0 -> 0 | I57: =0 -> 0 | J57: =Inputs!J34 -> 500 | K57: =Inputs!K34 -> 500 | L57: =Inputs!L34 -> 500 | M57: =Inputs!M34 -> 500 | N57: =Inputs!N34 -> 500
C58: Ending debt | D58: $mm | E58: =Inputs!E202+Inputs!E207 -> 9430 | F58: =Inputs!F202+Inputs!F207 -> 8933 | G58: =Inputs!G202+Inputs!G207 -> 8909 | H58: =Inputs!H202+Inputs!H207 -> 7961 | I58: =Inputs!I202+Inputs!I207 -> 7942 | J58: =MAX(0,J56-J57) -> 7442 | K58: =MAX(0,K56-K57) -> 6942 | L58: =MAX(0,L56-L57) -> 6442 | M58: =MAX(0,M56-M57) -> 5942 | N58: =MAX(0,N56-N57) -> 5442
C60: Beginning APIC | D60: $mm | E60: ="" | F60: =E63 -> 11484 | G60: =F63 -> 12412 | H60: =G63 -> 13409 | I60: =H63 -> 14195 | J60: =I63 -> 15158 | K60: =J63 -> 16031.809 | L60: =K63 -> 16941.808 | M60: =L63 -> 17893.607 | N60: =M63 -> 18889.505
C61: Stock compensation | D61: $mm | E61: =Inputs!E171 -> 638 | F61: =Inputs!F171 -> 755 | G61: =Inputs!G171 -> 804 | H61: =Inputs!H171 -> 709 | I61: =Inputs!I171 -> 715 | J61: =J16*Inputs!J31 -> 723.8088 | K61: =K16*Inputs!K31 -> 759.99924 | L61: =L16*Inputs!L31 -> 801.7992 | M61: =M16*Inputs!M31 -> 845.89815 | N61: =N16*Inputs!N31 -> 892.42255
C62: Stock issuance | D62: $mm | E62: =0 -> 0 | F62: =0 -> 0 | G62: =0 -> 0 | H62: =0 -> 0 | I62: =0 -> 0 | J62: =Inputs!J35 -> 150 | K62: =Inputs!K35 -> 150 | L62: =Inputs!L35 -> 150 | M62: =Inputs!M35 -> 150 | N62: =Inputs!N35 -> 150
C63: Ending APIC | D63: $mm | E63: =Inputs!E211 -> 11484 | F63: =Inputs!F211 -> 12412 | G63: =Inputs!G211 -> 13409 | H63: =Inputs!H211 -> 14195 | I63: =Inputs!I211 -> 15158 | J63: =J60+J61+J62 -> 16031.809 | K63: =K60+K61+K62 -> 16941.808 | L63: =L60+L61+L62 -> 17893.607 | M63: =M60+M61+M62 -> 18889.505 | N63: =N60+N61+N62 -> 19931.928
C65: Beginning retained earnings | D65: $mm | E65: ="" | F65: =E69 -> 3476 | G65: =F69 -> 1358 | H65: =G69 -> 965 | I65: =H69 -> -727 | J65: =I69 -> -155 | K65: =J69 -> 393.40381 | L65: =K69 -> 1289.194 | M65: =L69 -> 2581.0187 | N65: =M69 -> 4297.0169
C66: Net income | D66: $mm | E66: =Inputs!E167 -> 6046 | F66: =Inputs!F167 -> 5070 | G66: =Inputs!G167 -> 5700 | H66: =Inputs!H167 -> 3219 | I66: =Inputs!I167 -> 3108 | J66: =J28 -> 2995.4395 | K66: =K28 -> 3673.1321 | L66: =L28 -> 4479.5618 | M66: =M28 -> 5276.1862 | N66: =N28 -> 6056.3911
C67: Dividends | D67: $mm | E67: =Inputs!E184 -> 1837 | F67: =Inputs!F184 -> 2012 | G67: =Inputs!G184 -> 2169 | H67: =Inputs!H184 -> 2300 | I67: =Inputs!I184 -> 2407 | J67: =J28*Inputs!J32 -> 1947.0357 | K67: =K28*Inputs!K32 -> 2277.3419 | L67: =L28*Inputs!L32 -> 2687.7371 | M67: =M28*Inputs!M32 -> 3060.188 | N67: =N28*Inputs!N32 -> 3331.0151
C68: Share repurchases | D68: $mm | E68: =Inputs!E185 -> 4014 | F68: =Inputs!F185 -> 5480 | G68: =Inputs!G185 -> 4250 | H68: =Inputs!H185 -> 2985 | I68: =Inputs!I185 -> 146 | J68: =Inputs!J33 -> 500 | K68: =Inputs!K33 -> 500 | L68: =Inputs!L33 -> 500 | M68: =Inputs!M33 -> 500 | N68: =Inputs!N33 -> 500
C69: Ending retained earnings | D69: $mm | E69: =Inputs!E213 -> 3476 | F69: =Inputs!F213 -> 1358 | G69: =Inputs!G213 -> 965 | H69: =Inputs!H213 -> -727 | I69: =Inputs!I213 -> -155 | J69: =J65+J66-J67-J68 -> 393.40381 | K69: =K65+K66-K67-K68 -> 1289.194 | L69: =L65+L66-L67-L68 -> 2581.0187 | M69: =M65+M66-M67-M68 -> 4297.0169 | N69: =N65+N66-N67-N68 -> 6522.3929
B72: BALANCE SHEET
C74: Cash & equivalents | D74: $mm | E74: =Inputs!E191 -> 8574 | F74: =Inputs!F191 -> 7441 | G74: =Inputs!G191 -> 9860 | H74: =Inputs!H191 -> 7464 | I74: =Inputs!I191 -> 7563 | J74: =J135 -> 8289.9418 | K74: =K135 -> 9399.9331 | L74: =L135 -> 10889.808 | M74: =M135 -> 12895.154 | N74: =N135 -> 15509.557
C75: Short-term investments | D75: $mm | E75: =Inputs!E192 -> 4423 | F75: =Inputs!F192 -> 3234 | G75: =Inputs!G192 -> 1722 | H75: =Inputs!H192 -> 1687 | I75: =Inputs!I192 -> 1464 | J75: =J16*Inputs!J36 -> 1447.6176 | K75: =K16*Inputs!K36 -> 1469.3319 | L75: =L16*Inputs!L36 -> 1496.6918 | M75: =M16*Inputs!M36 -> 1522.6167 | N75: =N16*Inputs!N36 -> 1546.8658
C76: Accounts receivable | D76: $mm | E76: =Inputs!E193 -> 4667 | F76: =Inputs!F193 -> 4131 | G76: =Inputs!G193 -> 4427 | H76: =Inputs!H193 -> 4717 | I76: =Inputs!I193 -> 5931 | J76: =J39 -> 5816.9109 | K76: =K39 -> 5968.9438 | L76: =L39 -> 6150.7884 | M76: =M39 -> 6334.5798 | N76: =N39 -> 6519.9821
C77: Inventories | D77: $mm | E77: =Inputs!E194 -> 8420 | F77: =Inputs!F194 -> 8454 | G77: =Inputs!G194 -> 7519 | H77: =Inputs!H194 -> 7489 | I77: =Inputs!I194 -> 7501 | J77: =J40 -> 7584.1942 | K77: =K40 -> 7723.258 | L77: =L40 -> 7898.1981 | M77: =M40 -> 8172.5349 | N77: =N40 -> 8470.2718
C78: Prepaid & other current assets | D78: $mm | E78: =Inputs!E195 -> 2129 | F78: =Inputs!F195 -> 1942 | G78: =Inputs!G195 -> 1854 | H78: =Inputs!H195 -> 2005 | I78: =Inputs!I195 -> 2144 | J78: =J41 -> 2171.4264 | K78: =K41 -> 2229.3311 | L78: =L41 -> 2298.491 | M78: =M41 -> 2368.5148 | N78: =N41 -> 2439.2883
C79: Total current assets | D79: $mm | E79: =SUM(E74:E78) -> 28213 | F79: =SUM(F74:F78) -> 25202 | G79: =SUM(G74:G78) -> 25382 | H79: =SUM(H74:H78) -> 23362 | I79: =SUM(I74:I78) -> 24603 | J79: =SUM(J74:J78) -> 25310.091 | K79: =SUM(K74:K78) -> 26790.798 | L79: =SUM(L74:L78) -> 28733.977 | ... N79: =SUM(N74:N78) -> 34485.965
C80: PP&E, net | D80: $mm | E80: =Inputs!E196 -> 4791 | F80: =Inputs!F196 -> 5081 | G80: =Inputs!G196 -> 5000 | H80: =Inputs!H196 -> 4828 | I80: =Inputs!I196 -> 4796 | J80: =J54 -> 5085.5235 | K80: =K54 -> 5338.8566 | L80: =L54 -> 5552.6697 | M80: =M54 -> 5721.8494 | N80: =N54 -> 5840.839
C81: Operating lease assets | D81: $mm | E81: =Inputs!E197 -> 2926 | F81: =Inputs!F197 -> 2923 | G81: =Inputs!G197 -> 2718 | H81: =Inputs!H197 -> 2712 | I81: =Inputs!I197 -> 2838 | J81: =J16*Inputs!J37 -> 2895.2352 | K81: =K16*Inputs!K37 -> 2938.6637 | L81: =L16*Inputs!L37 -> 2993.3837 | M81: =M16*Inputs!M37 -> 3045.2334 | N81: =N16*Inputs!N37 -> 3093.7315
C82: Intangibles | D82: $mm | E82: =Inputs!E198 -> 286 | F82: =Inputs!F198 -> 274 | G82: =Inputs!G198 -> 259 | H82: =Inputs!H198 -> 259 | I82: =Inputs!I198 -> 259 | J82: =I82 -> 259 | K82: =J82 -> 259 | L82: =K82 -> 259 | M82: =L82 -> 259 | N82: =M82 -> 259
C83: Goodwill | D83: $mm | E83: =Inputs!E199 -> 284 | F83: =Inputs!F199 -> 281 | G83: =Inputs!G199 -> 240 | H83: =Inputs!H199 -> 240 | I83: =Inputs!I199 -> 240 | J83: =I83 -> 240 | K83: =J83 -> 240 | L83: =K83 -> 240 | M83: =L83 -> 240 | N83: =M83 -> 240
C84: Deferred tax & other assets | D84: $mm | E84: =Inputs!E200 -> 3821 | F84: =Inputs!F200 -> 3770 | G84: =Inputs!G200 -> 4511 | H84: =Inputs!H200 -> 5178 | I84: =Inputs!I200 -> 5674 | J84: =J16*Inputs!J26 -> 5838.7243 | K84: =K16*Inputs!K26 -> 6029.3273 | L84: =L16*Inputs!L26 -> 6254.0337 | M84: =M16*Inputs!M26 -> 6485.2192 | N84: =N16*Inputs!N26 -> 6722.9166
C85: Total assets | D85: $mm | E85: =SUM(E79:E84) -> 40321 | F85: =SUM(F79:F84) -> 37531 | G85: =SUM(G79:G84) -> 38110 | H85: =SUM(H79:H84) -> 36579 | I85: =SUM(I79:I84) -> 38410 | J85: =SUM(J79:J84) -> 39628.574 | K85: =SUM(K79:K84) -> 41596.646 | L85: =SUM(L79:L84) -> 44033.064 | ... N85: =SUM(N79:N84) -> 50642.452
C87: Accounts payable | D87: $mm | E87: =Inputs!E203 -> 3358 | F87: =Inputs!F203 -> 2862 | G87: =Inputs!G203 -> 2851 | H87: =Inputs!H203 -> 3479 | I87: =Inputs!I203 -> 3600 | J87: =J42 -> 3679.4606 | K87: =K42 -> 3900.6354 | L87: =L42 -> 4071.2361 | M87: =M42 -> 4341.6592 | N87: =N42 -> 4636.3593
C88: Current lease liabilities | D88: $mm | E88: =Inputs!E204 -> 420 | F88: =Inputs!F204 -> 425 | G88: =Inputs!G204 -> 477 | H88: =Inputs!H204 -> 502 | I88: =Inputs!I204 -> 478 | J88: =J81*Inputs!$M$142 -> 434.28528 | K88: =K81*Inputs!$M$142 -> 440.79956 | L88: =L81*Inputs!$M$142 -> 449.00755 | M88: =M81*Inputs!$M$142 -> 456.785 | N88: =N81*Inputs!$M$142 -> 464.05973
C89: Accrued liabilities | D89: $mm | E89: =Inputs!E205 -> 6220 | F89: =Inputs!F205 -> 5723 | G89: =Inputs!G205 -> 5725 | H89: =Inputs!H205 -> 5916 | I89: =Inputs!I205 -> 6092 | J89: =J43 -> 6369.5174 | K89: =K43 -> 6586.6601 | L89: =L43 -> 6842.0198 | M89: =M43 -> 7105.5445 | N89: =N43 -> 7377.3598
C90: Income taxes payable | D90: $mm | E90: =Inputs!E206 -> 222 | F90: =Inputs!F206 -> 240 | G90: =Inputs!G206 -> 534 | H90: =Inputs!H206 -> 669 | I90: =Inputs!I206 -> 377 | J90: =J44 -> 381.47709 | K90: =K44 -> 467.78302 | L90: =L44 -> 570.48397 | M90: =M44 -> 671.93617 | N90: =N44 -> 771.29732
C91: Current debt & notes payable | D91: $mm | E91: =Inputs!E202 -> 510 | F91: =Inputs!F202 -> 6 | G91: =Inputs!G202 -> 1006 | H91: =Inputs!H202 -> 0 | I91: =Inputs!I202 -> 2000 | J91: =Inputs!$M$141 -> 0 | K91: =Inputs!$M$141 -> 0 | L91: =Inputs!$M$141 -> 0 | M91: =Inputs!$M$141 -> 0 | N91: =Inputs!$M$141 -> 0
C92: Total current liabilities | D92: $mm | E92: =SUM(E87:E91) -> 10730 | F92: =SUM(F87:F91) -> 9256 | G92: =SUM(G87:G91) -> 10593 | H92: =SUM(H87:H91) -> 10566 | I92: =SUM(I87:I91) -> 12547 | J92: =SUM(J87:J91) -> 10864.74 | K92: =SUM(K87:K91) -> 11395.878 | L92: =SUM(L87:L91) -> 11932.747 | ... N92: =SUM(N87:N91) -> 13249.076
C93: Long-term debt | D93: $mm | E93: =Inputs!E207 -> 8920 | F93: =Inputs!F207 -> 8927 | G93: =Inputs!G207 -> 7903 | H93: =Inputs!H207 -> 7961 | I93: =Inputs!I207 -> 5942 | J93: =J58 -> 7442 | K93: =K58 -> 6942 | L93: =L58 -> 6442 | M93: =M58 -> 5942 | N93: =N58 -> 5442
C94: Long-term lease liabilities | D94: $mm | E94: =Inputs!E208 -> 2777 | F94: =Inputs!F208 -> 2786 | G94: =Inputs!G208 -> 2566 | H94: =Inputs!H208 -> 2550 | I94: =Inputs!I208 -> 2613 | J94: =J81-J88 -> 2460.9499 | K94: =K81-K88 -> 2497.8642 | L94: =L81-L88 -> 2544.3761 | M94: =M81-M88 -> 2588.4484 | N94: =N81-N88 -> 2629.6718
C95: Deferred tax & other liabilities | D95: $mm | E95: =Inputs!E209 -> 2613 | F95: =Inputs!F209 -> 2558 | G95: =Inputs!G209 -> 2618 | H95: =Inputs!H209 -> 2289 | I95: =Inputs!I209 -> 2443 | J95: =J16*Inputs!J28+J243 -> 2573.6711 | K95: =J95+(K16*Inputs!K28-J16*Inputs!J28)+K243 -> 2667.9013 | L95: =K95+(L16*Inputs!L28-K16*Inputs!K28)+L243 -> 2777.3149 | M95: =L95+(M16*Inputs!M28-L16*Inputs!L28)+M243 -> 2889.8062 | N95: =M95+(N16*Inputs!N28-M16*Inputs!M28)+N243 -> 3005.383
C96: Total liabilities | D96: $mm | E96: =SUM(E92:E95) -> 25040 | F96: =SUM(F92:F95) -> 23527 | G96: =SUM(G92:G95) -> 23680 | H96: =SUM(H92:H95) -> 23366 | I96: =SUM(I92:I95) -> 23545 | J96: =SUM(J92:J95) -> 23341.361 | K96: =SUM(K92:K95) -> 23503.644 | L96: =SUM(L92:L95) -> 23696.438 | ... N96: =SUM(N92:N95) -> 24326.131
C98: Common stock | D98: $mm | E98: =Inputs!E210 -> 3 | F98: =Inputs!F210 -> 3 | G98: =Inputs!G210 -> 3 | H98: =Inputs!H210 -> 3 | I98: =Inputs!I210 -> 3 | J98: =I98 -> 3 | K98: =J98 -> 3 | L98: =K98 -> 3 | M98: =L98 -> 3 | N98: =M98 -> 3
C99: APIC | D99: $mm | E99: =Inputs!E211 -> 11484 | F99: =Inputs!F211 -> 12412 | G99: =Inputs!G211 -> 13409 | H99: =Inputs!H211 -> 14195 | I99: =Inputs!I211 -> 15158 | J99: =J63 -> 16031.809 | K99: =K63 -> 16941.808 | L99: =L63 -> 17893.607 | M99: =M63 -> 18889.505 | N99: =N63 -> 19931.928
C100: AOCI | D100: $mm | E100: =Inputs!E212 -> 318 | F100: =Inputs!F212 -> 231 | G100: =Inputs!G212 -> 53 | H100: =Inputs!H212 -> -258 | I100: =Inputs!I212 -> -141 | J100: =I100 -> -141 | K100: =J100 -> -141 | L100: =K100 -> -141 | M100: =L100 -> -141 | N100: =M100 -> -141
C101: Retained earnings (deficit) | D101: $mm | E101: =Inputs!E213 -> 3476 | F101: =Inputs!F213 -> 1358 | G101: =Inputs!G213 -> 965 | H101: =Inputs!H213 -> -727 | I101: =Inputs!I213 -> -155 | J101: =J69 -> 393.40381 | K101: =K69 -> 1289.194 | L101: =L69 -> 2581.0187 | M101: =M69 -> 4297.0169 | N101: =N69 -> 6522.3929
C102: Total shareholders' equity | D102: $mm | E102: =SUM(E98:E101) -> 15281 | F102: =SUM(F98:F101) -> 14004 | G102: =SUM(G98:G101) -> 14430 | H102: =SUM(H98:H101) -> 13213 | I102: =SUM(I98:I101) -> 14865 | J102: =SUM(J98:J101) -> 16287.213 | K102: =SUM(K98:K101) -> 18093.002 | L102: =SUM(L98:L101) -> 20336.626 | ... N102: =SUM(N98:N101) -> 26316.321
C103: Total liabilities & equity | D103: $mm | E103: =E96+E102 -> 40321 | F103: =F96+F102 -> 37531 | G103: =G96+G102 -> 38110 | H103: =H96+H102 -> 36579 | I103: =I96+I102 -> 38410 | J103: =J96+J102 -> 39628.574 | K103: =K96+K102 -> 41596.646 | L103: =L96+L102 -> 44033.064 | ... N103: =N96+N102 -> 50642.452
C104: Balance sheet check | D104: $mm | E104: =ROUND(E85-E103,1) -> 0 | F104: =ROUND(F85-F103,1) -> 0 | G104: =ROUND(G85-G103,1) -> 0 | H104: =ROUND(H85-H103,1) -> 0 | I104: =ROUND(I85-I103,1) -> 0 | J104: =ROUND(J85-J103,1) -> 0 | K104: =ROUND(K85-K103,1) -> 0 | L104: =ROUND(L85-L103,1) -> 0 | ... N104: =ROUND(N85-N103,1) -> 0
B108: CASH FLOW STATEMENT
C110: Net income | D110: $mm | E110: =Inputs!E167 -> 6046 | F110: =Inputs!F167 -> 5070 | G110: =Inputs!G167 -> 5700 | H110: =Inputs!H167 -> 3219 | I110: =Inputs!I167 -> 3108 | J110: =J28 -> 2995.4395 | K110: =K28 -> 3673.1321 | L110: =L28 -> 4479.5618 | M110: =M28 -> 5276.1862 | N110: =N28 -> 6056.3911
C111: Depreciation & amortization | D111: $mm | E111: =Inputs!E170 -> 717 | F111: =Inputs!F170 -> 703 | G111: =Inputs!G170 -> 796 | H111: =Inputs!H170 -> 775 | I111: =Inputs!I170 -> 747 | J111: =J53 -> 772.06272 | K111: =K53 -> 810.66586 | L111: =L53 -> 855.25248 | M111: =M53 -> 902.29136 | N111: =N53 -> 951.91739
C112: Stock-based compensation | D112: $mm | E112: =Inputs!E171 -> 638 | F112: =Inputs!F171 -> 755 | G112: =Inputs!G171 -> 804 | H112: =Inputs!H171 -> 709 | I112: =Inputs!I171 -> 715 | J112: =J61 -> 723.8088 | K112: =K61 -> 759.99924 | L112: =L61 -> 801.7992 | M112: =M61 -> 845.89815 | N112: =N61 -> 892.42255
C113: Deferred income taxes | D113: $mm | E113: =Inputs!E172 -> -650 | F113: =Inputs!F172 -> -117 | G113: =Inputs!G172 -> -497 | H113: =Inputs!H172 -> -288 | I113: =Inputs!I172 -> -96 | J113: =J243 -> 16.213317 | K113: =K243 -> 17.023983 | L113: =L243 -> 17.960302 | M113: =M243 -> 18.948119 | N113: =N243 -> 19.990265
C114: Impairment, amortization & other noncash | D114: $mm | E114: =Inputs!E173 -> 123 | F114: =Inputs!F173 -> 156 | G114: =Inputs!G173 -> 48 | H114: =Inputs!H173 -> 33 | I114: =Inputs!I173 -> 50 | J114: =0 -> 0 | K114: =0 -> 0 | L114: =0 -> 0 | M114: =0 -> 0 | N114: =0 -> 0
C115: Net foreign currency adjustments | D115: $mm | E115: =Inputs!E174 -> -26 | F115: =Inputs!F174 -> -213 | G115: =Inputs!G174 -> -138 | H115: =Inputs!H174 -> 37 | I115: =Inputs!I174 -> 22 | J115: =0 -> 0 | K115: =0 -> 0 | L115: =0 -> 0 | M115: =0 -> 0 | N115: =0 -> 0
C116: Change in accounts receivable | D116: $mm | E116: =Inputs!E175 -> -504 | F116: =Inputs!F175 -> 489 | G116: =Inputs!G175 -> -329 | H116: =Inputs!H175 -> -257 | I116: =Inputs!I175 -> -1207 | J116: =-(J76-I76) -> 114.0891 | K116: =-(K76-J76) -> -152.0329 | L116: =-(L76-K76) -> -181.84457 | M116: =-(M76-L76) -> -183.79141 | N116: =-(N76-M76) -> -185.40234
C117: Change in inventories | D117: $mm | E117: =Inputs!E176 -> -1676 | F117: =Inputs!F176 -> -133 | G117: =Inputs!G176 -> 908 | H117: =Inputs!H176 -> 120 | I117: =Inputs!I176 -> -31 | J117: =-(J77-I77) -> -83.194199 | K117: =-(K77-J77) -> -139.06383 | L117: =-(L77-K77) -> -174.94003 | M117: =-(M77-L77) -> -274.33688 | N117: =-(N77-M77) -> -297.73684
C118: Change in prepaids, ROU & other assets | D118: $mm | E118: =Inputs!E177 -> -845 | F118: =Inputs!F177 -> -644 | G118: =Inputs!G177 -> -260 | H118: =Inputs!H177 -> -224 | I118: =Inputs!I177 -> 519 | J118: =-(SUM(J78,J81,J84)-SUM(I78,I81,I84)) -> -249.38592 | K118: =-(SUM(K78,K81,K84)-SUM(J78,J81,J84)) -> -291.93622 | L118: =-(SUM(L78,L81,L84)-SUM(K78,K81,K84)) -> -348.58632 | M118: =-(SUM(M78,M81,M84)-SUM(L78,L81,L84)) -> -353.05891 | N118: =-(SUM(N78,N81,N84)-SUM(M78,M81,M84)) -> -356.96902
C119: Change in AP, accrued, leases & other liabilities | D119: $mm | E119: =Inputs!E178 -> 1365 | F119: =Inputs!F178 -> -225 | G119: =Inputs!G178 -> 397 | H119: =Inputs!H178 -> -426 | I119: =Inputs!I178 -> -959 | J119: =SUM(J87:J90,J94)-SUM(I87:I90,I94) -> 165.69028 | K119: =SUM(K87:K90,K94)-SUM(J87:J90,J94) -> 568.05192 | L119: =SUM(L87:L90,L94)-SUM(K87:K90,K94) -> 583.38138 | M119: =SUM(M87:M90,M94)-SUM(L87:L90,L94) -> 687.24962 | N119: =SUM(N87:N90,N94)-SUM(M87:M90,M94) -> 714.37468
C120: Other operating adjustments | D120: $mm | E120: =0 -> 0 | F120: =0 -> 0 | G120: =0 -> 0 | H120: =0 -> 0 | I120: =0 -> 0 | J120: =J16*Inputs!J28-I95 -> 114.45776 | K120: =K16*Inputs!K28-J16*Inputs!J28 -> 77.206272 | L120: =L16*Inputs!L28-K16*Inputs!K28 -> 91.453242 | M120: =M16*Inputs!M28-L16*Inputs!L28 -> 93.54324 | N120: =N16*Inputs!N28-M16*Inputs!M28 -> 95.586491
C121: Operating cash flow tie-out | D121: $mm | E121: =E122-SUM(E110:E120) -> 0 | F121: =F122-SUM(F110:F120) -> 0 | G121: =G122-SUM(G110:G120) -> 0 | H121: =H122-SUM(H110:H120) -> 0 | I121: =I122-SUM(I110:I120) -> 0 | J121: =0 -> 0 | K121: =0 -> 0 | L121: =0 -> 0 | M121: =0 -> 0 | N121: =0 -> 0
C122: Cash from operations | D122: $mm | E122: =Inputs!E179 -> 5188 | F122: =Inputs!F179 -> 5841 | G122: =Inputs!G179 -> 7429 | H122: =Inputs!H179 -> 3698 | I122: =Inputs!I179 -> 2868 | J122: =SUM(J110:J120) -> 4569.1813 | K122: =SUM(K110:K120) -> 5323.0464 | L122: =SUM(L110:L120) -> 6124.0375 | M122: =SUM(M110:M120) -> 7012.9295 | N122: =SUM(N110:N120) -> 7890.5743
C124: Capital expenditures | D124: $mm | E124: =-Inputs!E180 -> -758 | F124: =-Inputs!F180 -> -969 | G124: =-Inputs!G180 -> -812 | H124: =-Inputs!H180 -> -430 | I124: =-Inputs!I180 -> -684 | J124: =-J52 -> -1061.5862 | K124: =-K52 -> -1063.9989 | L124: =-L52 -> -1069.0656 | M124: =-M52 -> -1071.471 | N124: =-N52 -> -1070.9071
C125: Other investing activities | D125: $mm | E125: =E126-E124 -> -766 | F125: =F126-F124 -> 1533 | G125: =G126-G124 -> 1706 | H125: =H126-H124 -> 155 | I125: =I126-I124 -> 196 | J125: =-(J75-I75) -> 16.3824 | K125: =-(K75-J75) -> -21.714264 | L125: =-(L75-K75) -> -27.359973 | M125: =-(M75-L75) -> -25.924841 | N125: =-(N75-M75) -> -24.24908
C126: Cash from investing | D126: $mm | E126: =Inputs!E181 -> -1524 | F126: =Inputs!F181 -> 564 | G126: =Inputs!G181 -> 894 | H126: =Inputs!H181 -> -275 | I126: =Inputs!I181 -> -488 | J126: =SUM(J124:J125) -> -1045.2038 | K126: =SUM(K124:K125) -> -1085.7132 | L126: =SUM(L124:L125) -> -1096.4256 | M126: =SUM(M124:M125) -> -1097.3958 | N126: =SUM(N124:N125) -> -1095.1561
...
